{
    "success": true,
    "description": "Successfully fetched",
    "elementsList": [
      {
        "id": "home",
        "displayName": "Home",
        "navigationUrl": "/home"
      },
      {
        "id": "experience",
        "displayName": "Experience",
        "navigationUrl": "/projects"
      },
      {
        "id": "skills",
        "displayName": "Skills",
        "navigationUrl": "/skills"
      },
      {
        "id": "achievements",
        "displayName": "achievements",
        "navigationUrl": "/achievements"
      },
      {
        "id": "about",
        "displayName": "About",
        "navigationUrl": "/about"
      }
    ]
}